llm_uv_tool/__init__.py
llm_uv_tool-0.1.3.dist-info/METADATA
llm_uv_tool-0.1.3.dist-info/WHEEL
llm_uv_tool-0.1.3.dist-info/entry_points.txt
llm_uv_tool-0.1.3.dist-info/licenses/AUTHORS.md
llm_uv_tool-0.1.3.dist-info/licenses/LICENSE
llm_uv_tool-0.1.3.dist-info/RECORD
