Metadata-Version: 2.4
Name: llm-uv-tool
Version: 0.1.3
Summary: A plugin for LLM that enables proper plugin management when installed via uv tool.
Project-URL: Documentation, https://github.com/joshuadavidthomas/llm-uv-tool#readme
Project-URL: Issues, https://github.com/joshuadavidthomas/llm-uv-tool/issues
Project-URL: Source, https://github.com/joshuadavidthomas/llm-uv-tool
Author-email: Josh Thomas <josh@joshthomas.dev>
License-File: AUTHORS.md
License-File: LICENSE
Classifier: Development Status :: 4 - Beta
Classifier: Environment :: Plugins
Classifier: License :: OSI Approved :: MIT License
Classifier: Operating System :: OS Independent
Classifier: Programming Language :: Python
Classifier: Programming Language :: Python :: 3
Classifier: Programming Language :: Python :: 3 :: Only
Classifier: Programming Language :: Python :: 3.10
Classifier: Programming Language :: Python :: 3.11
Classifier: Programming Language :: Python :: 3.12
Classifier: Programming Language :: Python :: 3.13
Classifier: Programming Language :: Python :: Implementation :: CPython
Requires-Python: >=3.10
Requires-Dist: llm>=0.24.2
Requires-Dist: uv>=0.6.14
